[{"name":"/Start Page","nodes":[{"id":"a4b7e4d4-c01d-1267-30b6-c2b448b90067","type":"Page","parameters":{},"ports":[],"children":[{"id":"fcfbc04f-65ce-bf80-9c09-6cdca911f3fe","type":"Text","parameters":{"textAlignX":"center","textStyle":"Display","text":"Hello World!!!"},"ports":[],"children":[]},{"id":"ecbf5b06-8e07-9f0f-675f-8e0e6b5d7aa5","type":"Group","parameters":{"paddingTop":{"value":16,"unit":"px"},"paddingBottom":{"value":16,"unit":"px"},"paddingLeft":{"value":16,"unit":"px"},"paddingRight":{"value":16,"unit":"px"},"rowGap":{"value":8,"unit":"px"}},"ports":[],"children":[{"id":"bb9d7c69-e677-b00b-ebd7-0a1e54da0505","type":"net.noodl.controls.textinput","parameters":{"label":"Text","startValue":"0"},"ports":[],"children":[]},{"id":"5fc7ac90-b8a9-beec-d1c4-514a7f480dfe","type":"net.noodl.controls.textinput","parameters":{"label":"Number","type":"number","startValue":"0"},"ports":[],"children":[]},{"id":"31dcfd0e-cabb-c90e-ee8c-a8ab563d1697","type":"net.noodl.controls.textinput","parameters":{"label":"Number","type":"number","startValue":"0","useLabel":true},"ports":[],"children":[]},{"id":"b302d18a-b425-3ddf-ca8a-4719ac25e138","type":"net.noodl.controls.textinput","parameters":{"fontSize":{"value":12,"unit":"px"},"fontFamily":"JosefinSans-VariableFont_wght.ttf","useLabel":false,"borderStyle":"none","sizeMode":"explicit","startValue":"123","height":{"value":20,"unit":"px"},"type":"number","placeholder":"","useIcon":false,"enabled":true,"visible":true,"paddingLeft":{"value":0,"unit":"px"},"paddingRight":{"value":0,"unit":"px"},"cssClassName":"TextInput_Number_Right"},"ports":[],"children":[]}]},{"id":"95aaf964-5107-f5a0-e7f8-2493860a090d","type":"Image","parameters":{"src":"Screenshot 2023-07-18 at 09.32.26.png"},"ports":[],"children":[]},{"id":"d3f3631f-2798-38f3-4859-4d0d275f5f80","type":"Image","parameters":{"src":"parlin-noise_001.png","sizeMode":"contentHeight","width":{"value":100,"unit":"px"}},"ports":[],"children":[]},{"id":"ad048458-1eea-1e42-1493-6070a7efc260","type":"net.noodl.controls.button","parameters":{},"ports":[],"children":[]}]},{"id":"2a48785a-a030-f298-7fd4-9b1f505111b3","type":"JavaScriptFunction","parameters":{"functionScript":"console.log(\"Hello from the Start page!\");"},"ports":[],"children":[]},{"id":"7bf5a9f3-eeb8-9625-3b15-3c7ea708a879","type":"CSS Definition","parameters":{"style":".TextInput_Number_Right {\r\n    text-align: right;\r\n\r\n    -webkit-appearance: textfield;\r\n    -moz-appearance: textfield;\r\n    appearance: textfield;\r\n}\r\n\r\n/* https://stackoverflow.com/a/45396364 */\r\n.TextInput_Number_Right::-webkit-inner-spin-button, \r\n.TextInput_Number_Right::-webkit-outer-spin-button { \r\n  -webkit-appearance: none;\r\n}"},"ports":[],"children":[]},{"id":"67d4ae2b-22da-a217-875c-e1b24de97da4","type":"PageInputs","parameters":{"queryParams":"test"},"ports":[],"children":[]},{"id":"04c3c170-7ab8-b050-3cb5-470c121e23a2","type":"RouterNavigate","parameters":{"router":"Main","target":"/nested"},"ports":[],"children":[]}],"connections":[{"sourceId":"a4b7e4d4-c01d-1267-30b6-c2b448b90067","sourcePort":"didMount","targetId":"2a48785a-a030-f298-7fd4-9b1f505111b3","targetPort":"run"},{"sourceId":"67d4ae2b-22da-a217-875c-e1b24de97da4","sourcePort":"pm-test","targetId":"fcfbc04f-65ce-bf80-9c09-6cdca911f3fe","targetPort":"text"},{"sourceId":"ad048458-1eea-1e42-1493-6070a7efc260","sourcePort":"onClick","targetId":"04c3c170-7ab8-b050-3cb5-470c121e23a2","targetPort":"navigate"}],"ports":[],"roots":[]}]